mongodb_connect/__init__.py
mongodb_connect/mongo_crud.py
testpackage_shashi-0.1.0.dist-info/LICENSE
testpackage_shashi-0.1.0.dist-info/METADATA
testpackage_shashi-0.1.0.dist-info/WHEEL
testpackage_shashi-0.1.0.dist-info/top_level.txt
testpackage_shashi-0.1.0.dist-info/RECORD
